__init__.py
ohsgpgn.py
ohsgpgn/__init__.py
ohsgpgn/ohsgpgn.py
ohsgpgn-0.0.41.dist-info/LICENSE.txt
ohsgpgn-0.0.41.dist-info/METADATA
ohsgpgn-0.0.41.dist-info/WHEEL
ohsgpgn-0.0.41.dist-info/top_level.txt
ohsgpgn-0.0.41.dist-info/RECORD
