Metadata-Version: 2.1
Name: ohsgpgn
Version: 0.0.41
Summary: oh Simple good password generator(ohsgpgn)
Home-page: http://pypi.python.org/pypi/ohsgpgn/
Author: OhYoungJooung
Author-email: wnapdlf05@gmail.com
License: LICENSE.txt
Platform: UNKNOWN
Classifier: Programming Language :: Python :: 3
Classifier: License :: OSI Approved :: MIT License
Classifier: Operating System :: OS Independent
Requires-Python: >=3.6
